agent/__init__.py
agent/agent/__init__.py
agent/agent/cot_agent.py
agent/agent/onescience_agent.py
agent/agent/react_agent.py
agent/agent/unit/__init__.py
agent/agent/unit/agent_state.py
agent/agent/unit/cot_runner.py
agent/agent/unit/generate_runner.py
agent/agent/unit/runner.py
agent/agent/unit/task_classify_runner.py
agent/agent/unit/tool_manager.py
agent/agent/unit/tool_runner.py
agent/llm/__init__.py
agent/llm/chat_model.py
agent/llm/embedding_model.py
agent/llm/rerank_model.py
agent/rag/__init__.py
agent/rag/rag_server.py
agent/rag/chunks/__init__.py
agent/rag/chunks/fixed_text_splitter.py
agent/rag/datasource/__init__.py
agent/rag/datasource/retrieval_methods.py
agent/rag/datasource/retrieval_service.py
agent/rag/datasource/keyword/__init__.py
agent/rag/datasource/keyword/keyword_base.py
agent/rag/datasource/keyword/keyword_factory.py
agent/rag/datasource/keyword/jieba/__init__.py
agent/rag/datasource/keyword/jieba/jieba_keyword_table_handler.py
agent/rag/datasource/keyword/jieba/stopwords.py
agent/rag/datasource/vdb/__init__.py
agent/rag/datasource/vdb/constant.py
agent/rag/datasource/vdb/vector_base.py
agent/rag/datasource/vdb/vector_factory.py
agent/rag/datasource/vdb/milvus/__init__.py
agent/rag/datasource/vdb/milvus/milvus_vector.py
agent/rag/datasource/vdb/milvus/schemas.py
agent/rag/docparser/__init__.py
agent/rag/docparser/doc_processor.py
agent/rag/docparser/helpers.py
agent/rag/docparser/markdown_parser.py
agent/rag/docparser/text_parser.py
agent/rag/postprocess/__init__.py
agent/rag/postprocess/rerank_base.py
agent/rag/postprocess/rerank_factory.py
agent/rag/postprocess/rerank_model.py
agent/rag/postprocess/weight_rerank.py
agent/rag/preprocess/__init__.py
agent/rag/preprocess/collection_preprocessor.py
agent/rag/preprocess/summary_preprocessor.py
agent/untils/__init__.py
agent/untils/until.py
onescience/__init__.py
onescience/constants.py
onescience/datapipes/__init__.py
onescience/datapipes/datapipe.py
onescience/datapipes/meta.py
onescience-0.2.0.dist-info/LICENSE
onescience-0.2.0.dist-info/METADATA
onescience-0.2.0.dist-info/WHEEL
onescience-0.2.0.dist-info/top_level.txt
onescience-0.2.0.dist-info/RECORD
